{
  "realm": "it-platform",
  "enabled": true,
  "displayName": "IT Platform",
  "displayNameHtml": "<div class=\"kc-logo-text\"><span>IT Platform</span></div>",
  "accessTokenLifespan": 300,
  "accessCodeLifespan": 60,
  "ssoSessionIdleTimeout": 1800,
  "ssoSessionMaxLifespan": 36000,
  "offlineSessionIdleTimeout": 2592000,
  "offlineSessionMaxLifespan": 5184000,
  "clientSessionIdleTimeout": 0,
  "clientSessionMaxLifespan": 0,
  "clientOfflineSessionIdleTimeout": 0,
  "clientOfflineSessionMaxLifespan": 0,
  "accessTokenLifeSso": 172800,
  "enabled": true,
  "sslRequired": "external",
  "registrationAllowed": false,
  "loginWithEmailAllowed": true,
  "duplicateEmailsAllowed": false,
  "resetPasswordAllowed": true,
  "editUsernameAllowed": false,
  "bruteForceProtected": true,
  "permanentLockout": false,
  "maxFailureWaitSeconds": 900,
  "minimumQuickLoginWaitSeconds": 60,
  "waitIncrementSeconds": 60,
  "quickLoginCheckMilliSeconds": 1000,
  "maxDeltaTimeSeconds": 43200,
  "failureFactor": 3,
  "roles": {
    "realm": [
      {
        "name": "admin",
        "description": "Administrator role with full access",
        "composite": false,
        "clientRole": false
      },
      {
        "name": "user",
        "description": "Standard user role",
        "composite": false,
        "clientRole": false
      },
      {
        "name": "auditor",
        "description": "Auditor role with read-only access to audit logs",
        "composite": false,
        "clientRole": false
      },
      {
        "name": "uma_authorization",
        "description": "${role_uma_authorization}",
        "composite": false,
        "clientRole": false
      },
      {
        "name": "offline_access",
        "description": "${role_offline-access}",
        "composite": false,
        "clientRole": false
      }
    ],
    "client": {
      "realm-management": [
        {
          "name": "view-users",
          "description": "${role_view-users}",
          "composite": true,
          "composites": {
            "client": {
              "realm-management": ["query-users", "query-groups", "query-clients"]
            }
          }
        },
        {
          "name": "query-users",
          "description": "${role_query-users}"
        },
        {
          "name": "query-groups",
          "description": "${role_query-groups}"
        },
        {
          "name": "query-clients",
          "description": "${role_query-clients}"
        },
        {
          "name": "manage-users",
          "description": "${role_manage-users}"
        }
      ],
      "portal-shell": [],
      "bff-auth": []
    }
  },
  "defaultRoles": ["user"],
  "requiredCredentials": ["password"],
  "passwordPolicy": "length(8) and specialChars(1) and digits(1) and upperCase(1)",
  "otpPolicyType": "Totp",
  "otpPolicyAlgorithm": "HmacSHA1",
  "otpPolicyInitialCounter": 0,
  "otpPolicyDigits": 6,
  "otpPolicyPeriod": 30,
  "otpPolicyCodeReusable": false,
  "clients": [
    {
      "clientId": "portal-shell",
      "name": "IT Platform Portal Shell",
      "description": "Next.js frontend application",
      "enabled": true,
      "clientAuthenticatorType": "client-secret",
      "secret": "${PORTAL_SHELL_CLIENT_SECRET:-portal-shell-secret}",
      "serviceAccountsEnabled": true,
      "authorizationServicesEnabled": true,
      "standardFlowEnabled": true,
      "implicitFlowEnabled": false,
      "directAccessGrantsEnabled": false,
      "publicClient": false,
      "frontchannelLogout": true,
      "protocol": "openid-connect",
      "fullScopeAllowed": true,
      "redirectUris": [
        "http://localhost:3000/*",
        "http://portal-shell:3000/*",
        "http://localhost:8080/*"
      ],
      "webOrigins": [
        "http://localhost:3000",
        "http://portal-shell:3000"
      ],
      "attributes": {
        "access.token.lifespan": "300",
        "access.token.signed.response.alg": "RS256",
        "id.token.signed.response.alg": "RS256",
        "tls.certificate.bound.tokens": "true",
        "refresh.token.timed": "true"
      },
      "defaultClientScopes": [
        "web-origins",
        "acr",
        "profile",
        "roles",
        "email",
        "basic"
      ],
      "optionalClientScopes": [
        "address",
        "phone",
        "offline_access",
        "microprofile-jwt"
      ]
    },
    {
      "clientId": "bff-auth",
      "name": "BFF Auth Service",
      "description": "Backend-for-Frontend authentication service",
      "enabled": true,
      "clientAuthenticatorType": "client-secret",
      "secret": "${BFF_AUTH_CLIENT_SECRET:-bff-auth-secret}",
      "serviceAccountsEnabled": true,
      "authorizationServicesEnabled": false,
      "standardFlowEnabled": false,
      "implicitFlowEnabled": false,
      "directAccessGrantsEnabled": true,
      "publicClient": false,
      "protocol": "openid-connect",
      "fullScopeAllowed": true,
      "attributes": {
        "access.token.lifespan": "300"
      },
      "defaultClientScopes": [
        "profile",
        "roles",
        "email"
      ],
      "optionalClientScopes": [
        "offline_access"
      ]
    }
  ],
  "clientScopes": [
    {
      "name": "web-origins",
      "description": "CORS allowed origins",
      "protocol": "openid-connect",
      "attributes": {
        "include.in.token.scope": "false",
        "display.on.consent.screen": "false"
      },
      "realmRoles": ["uma_authorization"]
    },
    {
      "name": "basic",
      "description": "Basic client scope",
      "protocol": "openid-connect",
      "attributes": {
        "include.in.token.scope": "true",
        "display.on.consent.screen": "true"
      }
    },
    {
      "name": "profile",
      "description": "User profile information",
      "protocol": "openid-connect",
      "attributes": {
        "include.in.token.scope": "true",
        "display.on.consent.screen": "true",
        "claim.name": "preferred_username"
      },
      "protocolMappers": [
        {
          "name": "username",
          "protocol": "openid-connect",
          "protocolMapper": "oidc-usermodel-property-mapper",
          "consentRequired": false,
          "config": {
            "user.attribute": "username",
            "claim.name": "preferred_username",
            "jsonType.label": "String"
          }
        },
        {
          "name": "given name",
          "protocol": "openid-connect",
          "protocolMapper": "oidc-usermodel-property-mapper",
          "consentRequired": true,
          "config": {
            "user.attribute": "firstName",
            "claim.name": "given_name",
            "jsonType.label": "String"
          }
        },
        {
          "name": "family name",
          "protocol": "openid-connect",
          "protocolMapper": "oidc-usermodel-property-mapper",
          "consentRequired": true,
          "config": {
            "user.attribute": "lastName",
            "claim.name": "family_name",
            "jsonType.label": "String"
          }
        }
      ]
    },
    {
      "name": "roles",
      "description": "User roles/permissions",
      "protocol": "openid-connect",
      "attributes": {
        "include.in.token.scope": "true",
        "display.on.consent.screen": "true"
      },
      "protocolMappers": [
        {
          "name": "realm roles",
          "protocol": "openid-connect",
          "protocolMapper": "oidc-usermodel-realm-role-mapper",
          "consentRequired": false,
          "config": {
            "multivalued": "true",
            "user.attribute": "realmAccess.roles",
            "claim.name": "realm_access.roles",
            "jsonType.label": "String"
          }
        }
      ]
    },
    {
      "name": "email",
      "description": "Email information",
      "protocol": "openid-connect",
      "attributes": {
        "include.in.token.scope": "true",
        "display.on.consent.screen": "true"
      },
      "protocolMappers": [
        {
          "name": "email",
          "protocol": "openid-connect",
          "protocolMapper": "oidc-usermodel-property-mapper",
          "consentRequired": true,
          "config": {
            "user.attribute": "email",
            "claim.name": "email",
            "jsonType.label": "String"
          }
        },
        {
          "name": "email verified",
          "protocol": "openid-connect",
          "protocolMapper": "oidc-usermodel-property-mapper",
          "consentRequired": true,
          "config": {
            "user.attribute": "emailVerified",
            "claim.name": "email_verified",
            "jsonType.label": "boolean"
          }
        }
      ]
    },
    {
      "name": "acr",
      "description": "Authentication Context Class Reference",
      "protocol": "openid-connect",
      "attributes": {
        "include.in.token.scope": "false",
        "display.on.consent.screen": "false"
      }
    },
    {
      "name": "offline_access",
      "description": "Offline access scope",
      "protocol": "openid-connect",
      "attributes": {
        "include.in.token.scope": "false",
        "display.on.consent.screen": "true",
        "consent.screen.text": "${offlineAccessScopeConsentText}"
      }
    }
  ],
  "users": [
    {
      "username": "admin",
      "enabled": true,
      "email": "admin@itplatform.internal",
      "firstName": "System",
      "lastName": "Administrator",
      "credentials": [
        {
          "type": "password",
          "value": "${ADMIN_USER_PASSWORD:-admin123}",
          "temporary": false
        }
      ],
      "realmRoles": ["admin", "user"]
    },
    {
      "username": "auditor",
      "enabled": true,
      "email": "auditor@itplatform.internal",
      "firstName": "System",
      "lastName": "Auditor",
      "credentials": [
        {
          "type": "password",
          "value": "${AUDITOR_USER_PASSWORD:-auditor123}",
          "temporary": false
        }
      ],
      "realmRoles": ["auditor", "user"]
    }
  ],
  "scopeMappings": [
    {
      "clientScope": "offline_access",
      "roles": ["offline_access"]
    }
  ],
  "authenticationFlows": [
    {
      "id": "68a5417a-73b3-4f2c-9c1a-1b2c3d4e5f6a",
      "alias": "Account verification options",
      "description": "Authentication with password only",
      "authenticationExecutions": [
        {
          "authenticator": "idp-review-profile",
          "authenticatorFlow": false,
          "requirement": "REQUIRED",
          "priority": 0,
          "userSetupAllowed": false,
          "autheticatorFlow": false
        }
      ]
    }
  ],
  "internationalization": {
    "supported": [],
    "defaultLanguage": "en"
  },
  "loginTheme": "keycloak",
  "accountTheme": "keycloak",
  "adminTheme": "keycloak",
  "emailTheme": "keycloak",
  "attributes": {
    "cibaBackchannelTokenDeliveryMode": "poll",
    "cibaExpiresIn": "120",
    "cibaAuthRequestedUserHint": "login_hint",
    "oauth2DeviceCodeLifespan": "600",
    "clientOfflineSessionMaxLifespan": "5184000",
    "oauth2DevicePollingInterval": "5",
    "clientSessionIdleTimeout": "0",
    "clientSessionMaxLifespan": "0",
    "parRequestUriLifespan": "60",
    "cibaInterval": "5"
  }
}
